{
  "teams": [
    {
      "name": "Serenity",
      "contact": "+256 788 228821",
      "p": 5,
      "w": 2,
      "d": 0,
      "l": 3,
      "gf": 4,
      "ga": 9,
      "gd": -5,
      "pts": 6
    },
    {
      "name": "Apps dooms",
      "contact": "+256 709 187830",
      "p": 3,
      "w": 2,
      "d": 1,
      "l": 0,
      "gf": 13,
      "ga": 6,
      "gd": 7,
      "pts": 7
    },
    {
      "name": "Africhester",
      "contact": "+256779085558",
      "p": 7,
      "w": 4,
      "d": 1,
      "l": 2,
      "gf": 10,
      "ga": 4,
      "gd": 6,
      "pts": 13
    },
    {
      "name": "Inter miami",
      "contact": "+256 744 660665",
      "p": 5,
      "w": 1,
      "d": 0,
      "l": 4,
      "gf": 3,
      "ga": 11,
      "gd": -8,
      "pts": 3
    }
  ],
  "fixtures": [
    {
      "home": "Apps dooms",
      "away": "Serenity",
      "hgoals": 5,
      "agoals": 2,
      "date": "2026-01-08",
      "time": "20:00",
      "matchday": 1
    },
    {
      "home": "Africhester",
      "away": "Serenity",
      "hgoals": 3,
      "agoals": 0,
      "date": "2026-01-10",
      "time": "20:00",
      "matchday": 2
    },
    {
      "home": "Africhester",
      "away": "Apps dooms",
      "hgoals": 3,
      "agoals": 3,
      "date": "2026-01-11",
      "time": "20:00",
      "matchday": 2
    },
    {
      "home": "Inter miami",
      "away": "Serenity",
      "hgoals": 1,
      "agoals": 2,
      "date": "2026-01-15",
      "time": "20:00",
      "matchday": 3
    },
    {
      "home": "Inter miami",
      "away": "Apps dooms",
      "hgoals": 1,
      "agoals": 5,
      "date": "2026-01-16",
      "time": "20:00",
      "matchday": 3
    },
    {
      "home": "Inter miami",
      "away": "Africhester",
      "hgoals": 1,
      "agoals": 4,
      "date": "2026-01-17",
      "time": "20:00",
      "matchday": 3
    }
  ]
}